README.txt
setup.py
Products/__init__.py
Products.MigrateExternalMethods.egg-info/PKG-INFO
Products.MigrateExternalMethods.egg-info/SOURCES.txt
Products.MigrateExternalMethods.egg-info/dependency_links.txt
Products.MigrateExternalMethods.egg-info/entry_points.txt
Products.MigrateExternalMethods.egg-info/namespace_packages.txt
Products.MigrateExternalMethods.egg-info/not-zip-safe
Products.MigrateExternalMethods.egg-info/requires.txt
Products.MigrateExternalMethods.egg-info/top_level.txt
Products/MigrateExternalMethods/__init__.py
Products/MigrateExternalMethods/changes.txt
Products/MigrateExternalMethods/readme.txt
Products/MigrateExternalMethods/Extensions/__init__.py
Products/MigrateExternalMethods/Extensions/migrate.py