Metadata-Version: 1.0
Name: Products.MigrateExternalMethods
Version: 1.0.1
Summary: A product that converts existing External Methods that used to live in the Extensions folder to a product folder
Home-page: http://www.nidelven-it.no/d
Author: Morten W. Petersen
Author-email: info@nidelven-it.no
License: GPL
Keywords: python zope plone silva cmf migration developers
Platform: UNKNOWN
Classifier: Programming Language :: Python
Classifier: Framework :: Zope2
Classifier: Framework :: Plone
